HowToDesignProgramsSecondEdition/README.md
HowToDesignProgramsSecondEdition/__init__.py
HowToDesignProgramsSecondEdition/__main__.py
HowToDesignProgramsSecondEdition/file.epub
HowToDesignProgramsSecondEdition/index.html
HowToDesignProgramsSecondEdition/css/__init__.py
HowToDesignProgramsSecondEdition/css/annotations.css
HowToDesignProgramsSecondEdition/css/main.css
HowToDesignProgramsSecondEdition/css/normalize.css
HowToDesignProgramsSecondEdition/css/popup.css
HowToDesignProgramsSecondEdition/font/__init__.py
HowToDesignProgramsSecondEdition/font/fontello.eot
HowToDesignProgramsSecondEdition/font/fontello.svg
HowToDesignProgramsSecondEdition/font/fontello.ttf
HowToDesignProgramsSecondEdition/font/fontello.woff
HowToDesignProgramsSecondEdition/img/__init__.py
HowToDesignProgramsSecondEdition/img/annotator-glyph-sprite.png
HowToDesignProgramsSecondEdition/img/annotator-icon-sprite.png
HowToDesignProgramsSecondEdition/img/apple-touch-icon.png
HowToDesignProgramsSecondEdition/img/cancelfullscreen.png
HowToDesignProgramsSecondEdition/img/close.png
HowToDesignProgramsSecondEdition/img/fullscreen.png
HowToDesignProgramsSecondEdition/img/loader.gif
HowToDesignProgramsSecondEdition/img/menu-icon.png
HowToDesignProgramsSecondEdition/img/save.png
HowToDesignProgramsSecondEdition/img/saved.png
HowToDesignProgramsSecondEdition/img/settings-s.png
HowToDesignProgramsSecondEdition/img/settings.png
HowToDesignProgramsSecondEdition/img/star.png
HowToDesignProgramsSecondEdition/js/__init__.py
HowToDesignProgramsSecondEdition/js/epub.js
HowToDesignProgramsSecondEdition/js/epub.min.js
HowToDesignProgramsSecondEdition/js/epub.min.map
HowToDesignProgramsSecondEdition/js/hooks.min.js
HowToDesignProgramsSecondEdition/js/hooks.min.map
HowToDesignProgramsSecondEdition/js/reader.js
HowToDesignProgramsSecondEdition/js/reader.js.map
HowToDesignProgramsSecondEdition/js/reader.min.js
HowToDesignProgramsSecondEdition/js/reader.min.map
HowToDesignProgramsSecondEdition/js/hooks/__init__.py
how_to_design_programs_second_edition-2024.3.2.0.dist-info/METADATA
how_to_design_programs_second_edition-2024.3.2.0.dist-info/WHEEL
how_to_design_programs_second_edition-2024.3.2.0.dist-info/entry_points.txt
how_to_design_programs_second_edition-2024.3.2.0.dist-info/top_level.txt
how_to_design_programs_second_edition-2024.3.2.0.dist-info/RECORD
